qxenonsign/__init__.py
qxenonsign/core.py
fourQtest-1.0.0.dist-info/METADATA
fourQtest-1.0.0.dist-info/WHEEL
fourQtest-1.0.0.dist-info/top_level.txt
fourQtest-1.0.0.dist-info/RECORD
