Metadata-Version: 2.1
Name: fourQtest
Version: 1.0.0
Summary: Qtest
Home-page: UNKNOWN
Author: fourchains
Author-email: fourchains.work@gmail.com
License: UNKNOWN
Platform: UNKNOWN
Classifier: Programming Language :: Python :: 3
Classifier: License :: OSI Approved :: MIT License
Classifier: Operating System :: OS Independent
Requires-Python: >=3.7
Requires-Dist: numpy
Requires-Dist: requests
Requires-Dist: pydantic
Requires-Dist: pyngrok
Requires-Dist: flask
